[
    {
        "file": "bai-viet-thu-hai.md",
        "title": "Tối ưu hóa Cơ sở dữ liệu: Indexing và Cache",
        "summary": "Một bài viết sâu hơn về các kỹ thuật Indexing và sử dụng Cache để tăng tốc độ truy vấn cơ sở dữ liệu.",
        "date": "2025-11-20",
        "cover": "../assets/images/cover2.jpg"
    },
    {
        "file": "bai-viet-dau-tien.md",
        "title": "Hướng Dẫn Lập Trình Cơ Bản với C++",
        "summary": "Giới thiệu về ngôn ngữ C++ và tại sao bạn nên học nó cho các dự án hiệu suất cao.",
        "date": "2025-11-06",
        "cover": "../assets/images/cover1.jpg"
    }
]